autosaver/__init__.py
autosaver/banks/__init__.py
autosaver/banks/bank.py
autosaver/banks/monzo.py
autosaver/banks/oauthbank.py
autosaver/banks/starling.py
autosaver-0.1.0.dist-info/WHEEL
autosaver-0.1.0.dist-info/METADATA
autosaver-0.1.0.dist-info/RECORD
