Metadata-Version: 2.1
Name: autosaver
Version: 0.1.0
Summary: 
Author: Richard Morrison
Author-email: richard@rmorrison.net
Requires-Python: >=3.8,<4.0
Classifier: Programming Language :: Python :: 3
Classifier: Programming Language :: Python :: 3.8
Requires-Dist: requests-oauthlib (>=1.3.0,<2.0.0)
